<?xml version="1.0"?>
<Chunk xmlns:xsd="http://www.w3.org/2001/XMLSchema" xmlns:xsi="http://www.w3.org/2001/XMLSchema-instance">
  <state>VisitedIsland</state>
  <coords>
    <x>17</x>
    <y>37</y>
  </coords>
  <islandDatas>
    <IslandData>
      <worldPosition>
        <x>-19.8808823</x>
        <y>1.5596981</y>
      </worldPosition>
      <worldRotation>177.7579</worldRotation>
      <index>0</index>
      <coords>
        <x>17</x>
        <y>37</y>
      </coords>
      <containsFormula>false</containsFormula>
      <storyManager>
        <hasBeenPlayed>true</hasBeenPlayed>
        <storyHandlers>
          <StoryHandler>
            <row>0</row>
            <col>0</col>
            <fallBackLayer>0</fallBackLayer>
            <storyID>19</storyID>
            <storyType>Normal</storyType>
            <contentDecals>
              <contentDecal>
                <row>1</row>
                <col>3</col>
                <decal>1</decal>
              </contentDecal>
              <contentDecal>
                <row>3</row>
                <col>19</col>
                <decal>1</decal>
              </contentDecal>
              <contentDecal>
                <row>8</row>
                <col>18</col>
                <decal>2</decal>
              </contentDecal>
            </contentDecals>
            <loots />
            <crews>
              <Crew>
                <hostile>false</hostile>
                <row>0</row>
                <col>9</col>
                <MemberIDs>
                  <Member>
                    <id>90</id>
                    <Name>Quincy</Name>
                    <health>100</health>
                    <maxHealth>100</maxHealth>
                    <currentHunger>0</currentHunger>
                    <Lvl>4</Lvl>
                    <xp>0</xp>
                    <skillPoints>0</skillPoints>
                    <specialSkillsIndexes>
                      <int>9</int>
                      <int>10</int>
                    </specialSkillsIndexes>
                    <stats>
                      <int>1</int>
                      <int>3</int>
                      <int>1</int>
                      <int>2</int>
                    </stats>
                    <daysOnBoard>0</daysOnBoard>
                    <equipedWeapon>
                      <ID>82</ID>
                      <englishName>Fine Lame</englishName>
                      <frenchName>Grande serpe</frenchName>
                      <value>41</value>
                      <price>63</price>
                      <weight>8</weight>
                      <level>4</level>
                      <spriteID>3</spriteID>
                      <description>It's just your basic fine lame</description>
                      <weaponType>Stick</weaponType>
                      <category>Weapon</category>
                    </equipedWeapon>
                    <equipedCloth>
                      <ID>171</ID>
                      <englishName>Rusty breastplate</englishName>
                      <frenchName>Cuirasse rouillée</frenchName>
                      <value>43</value>
                      <price>67</price>
                      <weight>8</weight>
                      <level>4</level>
                      <spriteID>1</spriteID>
                      <description>It's just your basic rusty breastplate</description>
                      <weaponType>Distance</weaponType>
                      <category>Clothes</category>
                    </equipedCloth>
                    <job>Surgeon</job>
                    <characterIDS>
                      <int>7</int>
                      <int>7</int>
                      <int>3</int>
                      <int>8</int>
                      <int>9</int>
                      <int>6</int>
                      <int>0</int>
                      <int>2</int>
                      <int>1</int>
                      <int>0</int>
                      <int>7</int>
                      <int>10</int>
                      <int>8</int>
                      <int>6</int>
                      <int>7</int>
                      <int>0</int>
                    </characterIDS>
                  </Member>
                </MemberIDs>
              </Crew>
            </crews>
          </StoryHandler>
        </storyHandlers>
      </storyManager>
    </IslandData>
    <IslandData>
      <worldPosition>
        <x>11.7861128</x>
        <y>-18.2961617</y>
      </worldPosition>
      <worldRotation>211.059357</worldRotation>
      <index>1</index>
      <coords>
        <x>17</x>
        <y>37</y>
      </coords>
      <containsFormula>false</containsFormula>
      <storyManager>
        <hasBeenPlayed>true</hasBeenPlayed>
        <storyHandlers>
          <StoryHandler>
            <row>0</row>
            <col>0</col>
            <fallBackLayer>0</fallBackLayer>
            <storyID>7</storyID>
            <storyType>Normal</storyType>
            <contentDecals>
              <contentDecal>
                <row>0</row>
                <col>2</col>
                <decal>2</decal>
              </contentDecal>
              <contentDecal>
                <row>15</row>
                <col>8</col>
                <decal>1</decal>
              </contentDecal>
              <contentDecal>
                <row>15</row>
                <col>13</col>
                <decal>1</decal>
              </contentDecal>
              <contentDecal>
                <row>0</row>
                <col>16</col>
                <decal>0</decal>
              </contentDecal>
              <contentDecal>
                <row>2</row>
                <col>20</col>
                <decal>1</decal>
              </contentDecal>
              <contentDecal>
                <row>15</row>
                <col>8</col>
                <decal>1</decal>
              </contentDecal>
              <contentDecal>
                <row>15</row>
                <col>13</col>
                <decal>1</decal>
              </contentDecal>
              <contentDecal>
                <row>0</row>
                <col>20</col>
                <decal>1</decal>
              </contentDecal>
              <contentDecal>
                <row>0</row>
                <col>50</col>
                <decal>0</decal>
              </contentDecal>
              <contentDecal>
                <row>0</row>
                <col>55</col>
                <decal>1</decal>
              </contentDecal>
              <contentDecal>
                <row>0</row>
                <col>66</col>
                <decal>1</decal>
              </contentDecal>
              <contentDecal>
                <row>1</row>
                <col>55</col>
                <decal>1</decal>
              </contentDecal>
              <contentDecal>
                <row>15</row>
                <col>8</col>
                <decal>1</decal>
              </contentDecal>
              <contentDecal>
                <row>16</row>
                <col>13</col>
                <decal>1</decal>
              </contentDecal>
            </contentDecals>
            <loots>
              <Loot>
                <row>1</row>
                <col>69</col>
                <ids>
                  <ArrayOfInt />
                  <ArrayOfInt />
                  <ArrayOfInt />
                  <ArrayOfInt />
                </ids>
                <weight>0</weight>
                <AllItems>
                  <ArrayOfItem />
                  <ArrayOfItem />
                  <ArrayOfItem />
                  <ArrayOfItem />
                </AllItems>
              </Loot>
            </loots>
            <crews />
          </StoryHandler>
        </storyHandlers>
      </storyManager>
    </IslandData>
  </islandDatas>
</Chunk>