<?xml version="1.0"?>
<Chunk xmlns:xsd="http://www.w3.org/2001/XMLSchema" xmlns:xsi="http://www.w3.org/2001/XMLSchema-instance">
  <state>UndiscoveredIsland</state>
  <islandDatas>
    <IslandData>
      <worldPosition>
        <x>-5.397032</x>
        <y>9.138145</y>
      </worldPosition>
      <worldRotation>144.140091</worldRotation>
      <storyManager>
        <hasBeenPlayed>false</hasBeenPlayed>
        <storyHandlers>
          <StoryHandler>
            <row>0</row>
            <col>0</col>
            <fallBackLayer>0</fallBackLayer>
            <storyID>2</storyID>
            <storyType>Normal</storyType>
            <contentDecals />
            <loots />
            <crews />
          </StoryHandler>
        </storyHandlers>
      </storyManager>
    </IslandData>
    <IslandData>
      <worldPosition>
        <x>-18.5618172</x>
        <y>11.7811432</y>
      </worldPosition>
      <worldRotation>275.0587</worldRotation>
      <storyManager>
        <hasBeenPlayed>false</hasBeenPlayed>
        <storyHandlers>
          <StoryHandler>
            <row>0</row>
            <col>0</col>
            <fallBackLayer>0</fallBackLayer>
            <storyID>2</storyID>
            <storyType>Normal</storyType>
            <contentDecals />
            <loots />
            <crews />
          </StoryHandler>
        </storyHandlers>
      </storyManager>
    </IslandData>
    <IslandData>
      <worldPosition>
        <x>7.07479429</x>
        <y>12.3695068</y>
      </worldPosition>
      <worldRotation>187.9351</worldRotation>
      <storyManager>
        <hasBeenPlayed>false</hasBeenPlayed>
        <storyHandlers>
          <StoryHandler>
            <row>0</row>
            <col>0</col>
            <fallBackLayer>0</fallBackLayer>
            <storyID>2</storyID>
            <storyType>Normal</storyType>
            <contentDecals />
            <loots />
            <crews />
          </StoryHandler>
        </storyHandlers>
      </storyManager>
    </IslandData>
  </islandDatas>
</Chunk>