<?xml version="1.0"?>
<Chunk xmlns:xsd="http://www.w3.org/2001/XMLSchema" xmlns:xsi="http://www.w3.org/2001/XMLSchema-instance">
  <state>UndiscoveredIsland</state>
  <islandDatas>
    <IslandData>
      <worldPosition>
        <x>-5.76804352</x>
        <y>-6.92516136</y>
      </worldPosition>
      <worldRotation>93.42411</worldRotation>
      <storyManager>
        <hasBeenPlayed>false</hasBeenPlayed>
        <storyHandlers>
          <StoryHandler>
            <row>0</row>
            <col>0</col>
            <fallBackLayer>0</fallBackLayer>
            <storyID>3</storyID>
            <storyType>Normal</storyType>
            <contentDecals />
            <loots />
            <crews />
          </StoryHandler>
        </storyHandlers>
      </storyManager>
    </IslandData>
    <IslandData>
      <worldPosition>
        <x>-1.44558716</x>
        <y>-6.45435143</y>
      </worldPosition>
      <worldRotation>152.465454</worldRotation>
      <storyManager>
        <hasBeenPlayed>false</hasBeenPlayed>
        <storyHandlers>
          <StoryHandler>
            <row>0</row>
            <col>0</col>
            <fallBackLayer>0</fallBackLayer>
            <storyID>3</storyID>
            <storyType>Normal</storyType>
            <contentDecals />
            <loots />
            <crews />
          </StoryHandler>
        </storyHandlers>
      </storyManager>
    </IslandData>
    <IslandData>
      <worldPosition>
        <x>-4.38438225</x>
        <y>-3.89533234</y>
      </worldPosition>
      <worldRotation>134.61116</worldRotation>
      <storyManager>
        <hasBeenPlayed>false</hasBeenPlayed>
        <storyHandlers>
          <StoryHandler>
            <row>0</row>
            <col>0</col>
            <fallBackLayer>0</fallBackLayer>
            <storyID>3</storyID>
            <storyType>Normal</storyType>
            <contentDecals />
            <loots />
            <crews />
          </StoryHandler>
        </storyHandlers>
      </storyManager>
    </IslandData>
    <IslandData>
      <worldPosition>
        <x>6.31367636</x>
        <y>-5.99492264</y>
      </worldPosition>
      <worldRotation>40.94433</worldRotation>
      <storyManager>
        <hasBeenPlayed>false</hasBeenPlayed>
        <storyHandlers>
          <StoryHandler>
            <row>0</row>
            <col>0</col>
            <fallBackLayer>0</fallBackLayer>
            <storyID>3</storyID>
            <storyType>Normal</storyType>
            <contentDecals />
            <loots />
            <crews />
          </StoryHandler>
        </storyHandlers>
      </storyManager>
    </IslandData>
  </islandDatas>
</Chunk>